{
  "storage_version": 1,
  "name": "fossi",
  "friendly_name": "Fossibot",
  "comment": "Fossi 2400 Portable Power Station",
  "esphome_version": "2025.12.2",
  "src_version": 1,
  "address": "fossi.local",
  "web_port": null,
  "esp_platform": "ESP32",
  "build_path": "C:\\Users\\danw\\Documents\\FossiESP\\ESP-FBot\\.esphome\\build\\fossi",
  "firmware_bin_path": "C:\\Users\\danw\\Documents\\FossiESP\\ESP-FBot\\.esphome\\build\\fossi\\.pioenvs\\fossi\\firmware.bin",
  "loaded_integrations": [
    "api",
    "binary_sensor",
    "ble_client",
    "esp32",
    "esp32_ble",
    "esp32_ble_client",
    "esp32_ble_tracker",
    "esphome",
    "external_components",
    "fbot",
    "logger",
    "md5",
    "mdns",
    "network",
    "number",
    "ota",
    "preferences",
    "safe_mode",
    "sensor",
    "sha256",
    "socket",
    "switch",
    "template",
    "wifi"
  ],
  "loaded_platforms": [
    "binary_sensor/fbot",
    "number/fbot",
    "ota/esphome",
    "sensor/fbot",
    "sensor/template",
    "switch/fbot"
  ],
  "no_mdns": false,
  "framework": "esp-idf",
  "core_platform": "esp32"
}
